codetalk/__init__.py
codetalk/asset.py
codetalk/backend.py
codetalk/config.py
codetalk/filtration.py
codetalk/formatter.py
codetalk/index.py
codetalk/logconf.py
codetalk/main.py
codetalk/spinner.py
codetalk/subcommand.py
codetalk/assets/logo.txt
codetalk/assets/version.txt
src/__init__.py
src/backend.py
src/config.py
src/filtration.py
src/formatter.py
src/index.py
src/logconf.py
src/main.py
src/spinner.py
src/subcommand.py
codetalk-0.3.1.dist-info/LICENSE.txt
codetalk-0.3.1.dist-info/METADATA
codetalk-0.3.1.dist-info/WHEEL
codetalk-0.3.1.dist-info/entry_points.txt
codetalk-0.3.1.dist-info/top_level.txt
codetalk-0.3.1.dist-info/RECORD
