Metadata-Version: 2.1
Name: codetalk
Version: 0.3.1
Summary: Talk to your code!
License-File: LICENSE.txt
Requires-Dist: filetype
Requires-Dist: gitpython
Requires-Dist: prompt-toolkit
Requires-Dist: pygments
Requires-Dist: requests
Requires-Dist: sseclient-py
